prefect_asimov/__init__.py
prefect_asimov/_version.py
prefect_asimov/py.typed
prefect_asimov-0.0.0.dist-info/METADATA
prefect_asimov-0.0.0.dist-info/WHEEL
prefect_asimov-0.0.0.dist-info/licenses/UNLICENSE
prefect_asimov-0.0.0.dist-info/RECORD
