Metadata-Version: 2.4
Name: prefect-asimov
Version: 0.0.0
Summary: Prefect integration with the ASIMOV platform.
Project-URL: Homepage, https://github.com/asimov-platform
Project-URL: Repository, https://github.com/asimov-platform/prefect-asimov
Project-URL: Changelog, https://github.com/asimov-platform/prefect-asimov/blob/master/CHANGES.md
Project-URL: Releases, https://github.com/asimov-platform/prefect-asimov/releases
Project-URL: Issues, https://github.com/asimov-platform/prefect-asimov/issues
Author-email: ASIMOV Protocol <support@asimov.so>
License-Expression: Unlicense
License-File: UNLICENSE
Requires-Python: >=3.9
Requires-Dist: prefect>=3.4
